markdown_include/__init__.py
markdown_include/include.py
tiangolo_markdown_include-0.7.0.dist-info/LICENSE.txt
tiangolo_markdown_include-0.7.0.dist-info/METADATA
tiangolo_markdown_include-0.7.0.dist-info/WHEEL
tiangolo_markdown_include-0.7.0.dist-info/top_level.txt
tiangolo_markdown_include-0.7.0.dist-info/RECORD
