Metadata-Version: 2.1
Name: tiangolo-markdown-include
Version: 0.7.0
Summary: This is an extension to Python-Markdown which provides an "include" function, similar to that found in LaTeX (and also the C pre-processor and Fortran). I originally wrote it for my FORD Fortran auto-documentation generator.
Home-page: https://github.com/tiangolo/markdown-include
Author: Sebastián Ramírez
Author-email: tiangolo@gmail.com
License: UNKNOWN
Download-URL: https://github.com/tiangolo/markdown-include/tarball/v0.7.0
Keywords: Markdown,typesetting,include,plugin,extension
Platform: UNKNOWN
Classifier: Development Status :: 5 - Production/Stable
Classifier: Intended Audience :: Developers
Classifier: Topic :: Internet :: WWW/HTTP :: Site Management
Classifier: Topic :: Software Development :: Documentation
Classifier: Topic :: Software Development :: Libraries :: Python Modules
Classifier: Topic :: Text Processing :: Filters
Classifier: Topic :: Text Processing :: Markup :: HTML
Classifier: License :: OSI Approved :: GNU General Public License v3 (GPLv3)
Classifier: Programming Language :: Python :: 2
Classifier: Programming Language :: Python :: 2.7
Classifier: Programming Language :: Python :: 3
Classifier: Programming Language :: Python :: 3.3
Classifier: Programming Language :: Python :: 3.4
Requires-Dist: markdown
